quak/__init__.py
quak/_util.py
quak/_version.py
quak/_widget.py
quak/widget.js
quak-0.3.4.dist-info/METADATA
quak-0.3.4.dist-info/WHEEL
quak-0.3.4.dist-info/licenses/LICENSE
quak-0.3.4.dist-info/RECORD
