Metadata-Version: 2.4
Name: quak
Version: 0.3.4
License-File: LICENSE
Requires-Python: >=3.8
Requires-Dist: anywidget>=0.9.0
Requires-Dist: duckdb>=1.0.0
Requires-Dist: pyarrow>=16.0.0
